setup.py
v03_distributions/Binomialdistribution.py
v03_distributions/Gaussiandistribution.py
v03_distributions/Generaldistribution.py
v03_distributions/__init__.py
v03_distributions.egg-info/PKG-INFO
v03_distributions.egg-info/SOURCES.txt
v03_distributions.egg-info/dependency_links.txt
v03_distributions.egg-info/not-zip-safe
v03_distributions.egg-info/top_level.txt