Metadata-Version: 1.0
Name: v03-distributions
Version: 0.1
Summary: Gaussian distributions
Home-page: UNKNOWN
Author: Jhon Nagasako
Author-email: test@test.com
License: UNKNOWN
Platform: UNKNOWN
